setup.py
shinkenplugins/__init__.py
shinkenplugins.plugins.environment_canada.egg-info/PKG-INFO
shinkenplugins.plugins.environment_canada.egg-info/SOURCES.txt
shinkenplugins.plugins.environment_canada.egg-info/dependency_links.txt
shinkenplugins.plugins.environment_canada.egg-info/entry_points.txt
shinkenplugins.plugins.environment_canada.egg-info/namespace_packages.txt
shinkenplugins.plugins.environment_canada.egg-info/requires.txt
shinkenplugins.plugins.environment_canada.egg-info/top_level.txt
shinkenplugins/plugins/__init__.py
shinkenplugins/plugins/environment_canada/__init__.py
shinkenplugins/plugins/environment_canada/environment_canada.py