Metadata-Version: 1.0
Name: shinkenplugins.plugins.environment-canada
Version: 1.2
Summary: Checks various environment metrics in Canada.
Home-page: https://github.com/savoirfairelinux/sfl-shinken-plugins
Author: Grégory Starck
Author-email: gregory.starck@savoirfairelinux.com
License: GPL3+
Platform: any
